{
  "partition_plan": {
    "tables": {
      "usertable": {
        "partitions": {
          "0": "0-120000",
          "1": "240000-360000",
          "2": "120000-240000",
          "3": "360000-480000",
          "4": "",
          "5": "",
          "6": "",
          "7": "",
          "8": "",
          "9": "",
          "10": "",
          "11": "",
          "12": "",
          "13": "",
          "14": "",
          "15": "",
          "16": "",
          "17": "480000-600000"
		}
        }
      }
  },
  "default_table": "usertable"
}
